{
  "sourceUrl": "https://www.dor.ms.gov/motor-vehicle/available-license-plates/specialty-license-plates",
  "scrapedAt": "2026-03-31",
  "status": "first-pass-partial",
  "notes": [
    "Extracted from the official Mississippi DOR specialty license plates page.",
    "This is a first-pass raw-name scrape for planning and curation, not yet a complete master dataset.",
    "Image URLs, categories, and variant relationships still need follow-up work.",
    "A second pass should verify missed entries and collect direct image URLs."
  ],
  "plateNames": [
    "100% Disabled Veteran Air Force",
    "100% Disabled Veteran Air Force Motorcycle",
    "100% Disabled Veteran Army",
    "100% Disabled Veteran Army Motorcycle",
    "100% Disabled Veteran Coast Guard",
    "100% Disabled Veteran Coast Guard Motorcycle",
    "100% Disabled Veteran Marine",
    "100% Disabled Veteran Marine Motorcycle",
    "100% Disabled Veteran Navy",
    "100% Disabled Veteran Navy Motorcycle",
    "2022 National Championship Ole Miss Baseball",
    "4 - H Club",
    "Active Reserve",
    "Afghanistan Veteran",
    "Air Medal",
    "Alcorn State University",
    "Alpha Kappa Alpha",
    "Alpha Phi Alpha",
    "Alzheimer’s Awareness",
    "Amateur Radio",
    "American Legion",
    "Antique Car",
    "Antique Car Vanity",
    "Antique Motorcycle",
    "Antique Motorcycle Vanity",
    "Antique Truck",
    "Antique Truck Vanity",
    "Apportioned Truck",
    "Auburn University",
    "Autism Awareness",
    "B16-B80",
    "Band of Choctaw Indians",
    "Bass - Department of Wildlife Fisheries and Parks",
    "Belhaven University",
    "Bicycle Share the Road",
    "Biloxi Public School District",
    "Blackout B-10",
    "Blackout F-10",
    "Blackout Motorcycle",
    "Blackout Passenger",
    "Blackout Pickup",
    "Board of Contractor",
    "Booneville School District",
    "Boy Scouts of America",
    "Breast Cancer Awareness",
    "Bronze Star",
    "Bronze Star Disabled",
    "Butterfly - Department of Wildlife Fisheries and Parks",
    "Catch A Dream Foundation",
    "Cattleman’s Foundation",
    "Children’s Advocacy Center",
    "Choose Life",
    "Church Bus",
    "Civil Air Patrol",
    "Coastal Conservation",
    "Colon Cancer Prevention",
    "Columbia School District",
    "Columbus Municipal School District",
    "Combat Veteran Air Force",
    "Combat Veteran Army",
    "Combat Veteran Coast Guard",
    "Combat Veteran Marine",
    "Combat Veteran Navy",
    "Dealer Demo",
    "Dealer Manufacturer",
    "Dealer Motorcycle",
    "Dealer New",
    "Dealer Trailer",
    "Dealer Used",
    "Dealer Wholesaler",
    "Deer - Department of Wildlife Fisheries and Parks",
    "Defense Freedom Medal",
    "Delta Sigma Theta",
    "Delta State University",
    "Delta Waterfowl",
    "Dental Hygienist",
    "Diabetic",
    "Diocese of Biloxi",
    "Disabled",
    "Disabled - Motorcycle",
    "Disabled American Veteran - Air Force",
    "Disabled American Veteran - Army",
    "Disabled American Veteran - Coast Guard",
    "Disabled American Veteran - Marine",
    "Disabled American Veteran - Navy",
    "Disabled American Veteran Less than 100%",
    "Disabled American Veteran Motorcycle - Air Force",
    "Disabled American Veteran Motorcycle - Army",
    "Disabled American Veteran Motorcycle - Coast Guard",
    "Disabled American Veteran Motorcycle - Marine",
    "Disabled American Veteran Motorcycle - Navy",
    "Disabled Veteran Motorcycle - Navy",
    "Distinguished Flying Cross",
    "Dixie National",
    "Down Syndrome Awareness",
    "Ducks Unlimited Inc",
    "Dyslexia Awareness",
    "East Central Attendance Center",
    "Electric Power Association",
    "Enterprise School District",
    "EV Mississippi",
    "Ex Prisoner of War",
    "Ex US House of Representative",
    "Ex US Senator",
    "F16-F80",
    "Fannie Lou Hamer Cancer Foundation",
    "Farm Families of Mississippi",
    "Female Veteran - Air Force",
    "Female Veteran - Army",
    "Female Veteran - Coast Guard",
    "Female Veteran - Marine",
    "Fire Fighters",
    "Fleet",
    "Fleet Trailer Rental",
    "Forestry Association",
    "Former Governor",
    "Friends of Children’s Hospital",
    "Friends of Jackson County Animal Shelter",
    "Gentry High School",
    "George County School District",
    "Germantown High School",
    "God Bless America - Sunflower Consolidated School Preservation",
    "Gold Star Air Force",
    "Gold Star Army",
    "Gold Star Coast Guard",
    "Gold Star Marine",
    "Gold Star Navy",
    "Government",
    "Government Motorcycle",
    "Governor",
    "Grand Lodge",
    "Grand Lodge - Motorcycle",
    "Gulf Coast Regional Tourism Partnership",
    "Gulf War Veteran",
    "Gulfport Police Athletic League",
    "Gulfport School District",
    "Harvest Permitees",
    "Hattiesburg School District",
    "Hearing Impaired",
    "Hearing Impaired - Motorcycle",
    "Hearse",
    "Heavy Truck Trailer",
    "Heroines of Jericho",
    "Historic Natchez/City of Natchez",
    "Historical",
    "Holmes Community College",
    "Honoring Fallen Officers",
    "Honoring Veterans",
    "Hummingbird - Department of Wildlife Fisheries and Parks",
    "I Care for Animals",
    "I Love Mississippi - Sunflower Consolidated School Preservation",
    "Institute for Marine Mammal Studies - Protect Dolphin",
    "Institute for Marine Mammal Studies - Shark",
    "Iraq Veteran",
    "Jackson State University",
    "Jackson Zoo",
    "Juvenile Diabetes",
    "Juvenile Diabetes Research Foundation",
    "Kappa Alpha Psi",
    "Kemp’s Ridley Sea Turtle",
    "Killed in Action",
    "Knights of Columbus",
    "Lab - Department of Wildlife Fisheries and Parks",
    "Louisiana State University",
    "Madison Jaguars",
    "Magnolia Heights School",
    "Mallard - Department of Wildlife Fisheries and Parks",
    "Marine Corps",
    "Maurice F Lucas, Sr., Grand Chapter of the Eastern Star",
    "Medal of Honor - Army",
    "Medal of Honor - Marine",
    "Merchant Marine",
    "Meridian Public School",
    "Millsaps College",
    "Mississippi After School Alliance",
    "Mississippi Aquarium",
    "Mississippi Association of Emergency Services",
    "Mississippi Blood Services, Inc",
    "Mississippi Children's Museum",
    "Mississippi College",
    "Mississippi Family Physicians",
    "Mississippi Golf Association",
    "Mississippi Home of the Blues",
    "Mississippi House of Representative",
    "Mississippi Law Enforcement Officers Association Supporter",
    "Mississippi Loggers Association",
    "Mississippi Motosteps",
    "Mississippi Motosteps - Motorcycle",
    "Mississippi Nurses Foundation",
    "Mississippi Organ Donor",
    "Mississippi Public Broadcasting",
    "Mississippi Senator",
    "Mississippi State Equine Association",
    "Mississippi State Parks",
    "Mississippi State University",
    "Mississippi Tennis Association",
    "Mississippi Toughest Kids Foundation",
    "Mississippi University for Women",
    "Mississippi Valley State University",
    "Mixed Martial Arts",
    "Motorcycle",
    "Motorcycle National Guard",
    "Motorcycle Trailer",
    "Motorcycle Vanity",
    "Motorcycle Vanity Trailer",
    "MS Law Enforcement Officer Association Supporter",
    "MS Sweet Potato",
    "MSU Baseball Championship",
    "MW Stringer Grand Lodge - F & AM Prince Hall Affiliated",
    "National Guard - Special",
    "National Rifle Association",
    "National Rifle Association - Trailer",
    "National Wild Turkey Federation",
    "Navy and Marine Corps",
    "Neshoba Central Rockets",
    "New Orleans Saints Football",
    "Oak Grove School",
    "Ocean Springs Athletic Foundation",
    "Ole Miss Welcome Home",
    "Olive Branch High School",
    "Omega Psi Phi",
    "Omega Psi Phi - Motorcycle",
    "Oxford School District",
    "Passenger",
    "Pearl Harbor",
    "Pearl Harbor - Motorcycle",
    "Pearl River Valley Water",
    "Pearl School District",
    "Petal School District",
    "Phi Beta Sigma",
    "Poplarville Public School District",
    "Private Trailer",
    "Profession of Pharmacy",
    "Professional Fire Fighter",
    "Professional Hair Designers",
    "Purple Heart - Disabled",
    "Purple Heart - Motorcycle",
    "Purple Heart - Original",
    "Rabbit - Department of Wildlife Fisheries and Parks",
    "Rankin County School District",
    "Realtors (Mississippi Association)",
    "Retired as Career Law Enforcement Officer",
    "Retired Troopers",
    "Ridgeland High School",
    "Rotary International",
    "Rust College",
    "School Bus",
    "Sheriff’s Office",
    "Sigma Gamma Rho Sorority Supporter",
    "Silver Star",
    "Soil Conservation",
    "Sons of Confederate Veterans",
    "Sons of Confederate Veterans - Motorcycle",
    "South Panola School District",
    "Speckled Trout - Department of Wildlife Fisheries and Parks",
    "St Jude Children’s Hospital",
    "St Martin High School",
    "St Patrick High School",
    "Starkville – Oktibbeha Football",
    "State Flag",
    "Stone County School District",
    "Street Rod",
    "Sunflower County Ministerial Alliance Counseling Services",
    "Support Teachers",
    "Taxi",
    "Temporary Truck",
    "Tougaloo College",
    "Tupelo Elvis Presley Fan Club",
    "Tupelo Public School",
    "Turkey - Department of Wildlife Fisheries and Parks",
    "University of Alabama",
    "University of Memphis",
    "University of Mississippi",
    "University of Southern Mississippi",
    "US House of Representative",
    "US Senator",
    "Vancleave Home Run Club",
    "Vanity Passenger",
    "Vanity Trailer",
    "Veteran Air Force",
    "Veteran Air Force - Motorcycle",
    "Veteran Army",
    "Veteran Army - Motorcycle",
    "Veteran Coast Guard",
    "Veteran Coast Guard - Motorcycle",
    "Veteran Marine",
    "Veteran Marine - Motorcycle",
    "Veteran Navy",
    "Veteran Navy - Motorcycle",
    "Veterans of Foreign Wars",
    "Vietnam Veteran",
    "Volunteer Service",
    "West Jones High School",
    "West Lauderdale Knights",
    "Wildlife Enforcement",
    "Wildlife Federation",
    "William Carey University",
    "Youth Soccer Association",
    "Zeta Phi Beta Sorority"
  ]
}
